sanitize_jhlong.py
sanitize_jhlong-1.0.4.dist-info/METADATA
sanitize_jhlong-1.0.4.dist-info/WHEEL
sanitize_jhlong-1.0.4.dist-info/top_level.txt
sanitize_jhlong-1.0.4.dist-info/RECORD
