Metadata-Version: 2.1
Name: sanitize_jhlong
Version: 1.0.4
Summary: 处理计时数据的一个函数
Author: jhlong
Author-email: jhlong2024@163.com
